{
    "RealtimeFireDanger": {
        "last_update": "2025-12-25 23:38 CT",
        "status": "updated",
        "runtime_sec": 12.95,
        "log": [
            "Fire Danger Map updated at 2025-12-25 23:38 CT",
            "Script runtime: 12.95 seconds"
        ]
    },
    "HumidityFiltered": {
        "last_update": "2025-12-25 23:38 CT",
        "status": "updated",
        "runtime_sec": 14.42,
        "log": [
            "RH% Filtered Map updated at 2025-12-25 23:38 CT",
            "Script runtime: 14.42 seconds"
        ]
    },
    "Humidity": {
        "last_update": "2025-12-22 14:38 CT",
        "status": "updated"
    },
    "WindFiltered": {
        "last_update": "2025-12-25 23:38 CT",
        "status": "updated",
        "runtime_sec": 14.82,
        "log": [
            "Wind Map updated at 2025-12-25 23:38 CT",
            "Script runtime: 14.82 seconds"
        ]
    },
    "Wind": {
        "last_update": "2025-12-22 14:38 CT",
        "status": "updated"
    },
    "RealTimeFuelMoisture": {
        "last_update": "2025-12-25 23:37 CT",
        "status": "updated",
        "runtime_sec": 11.88,
        "log": [
            "Fuel Moisture updated at 2025-12-25 23:37 CT",
            "Script runtime: 11.88 seconds"
        ]
    }
}